retry_pytest/__init__.py
retry_pytest/command.py
retry_pytest/custom_errors.py
retry_pytest/retry.py
retry_pytest-1.3.0.dist-info/licenses/LICENSE
retry_pytest-1.3.0.dist-info/METADATA
retry_pytest-1.3.0.dist-info/WHEEL
retry_pytest-1.3.0.dist-info/top_level.txt
retry_pytest-1.3.0.dist-info/RECORD
