Metadata-Version: 2.4
Name: retry_pytest
Version: 1.3.0
Summary: retry_pytest
Author-email: Alexander Evdokimov <1812gg@bk.ru>
License: GNU AGPL
Project-URL: Homepage, https://github.com/Shumodan/retry-pytest
Keywords: pytest,allure,retry
Classifier: Development Status :: 4 - Beta
Classifier: Programming Language :: Python :: 3
Classifier: Topic :: Software Development :: Testing
Classifier: License :: OSI Approved :: GNU Affero General Public License v3 or later (AGPLv3+)
Classifier: Operating System :: OS Independent
Classifier: Framework :: Pytest
Requires-Python: >=3.11
License-File: LICENSE
Requires-Dist: pytest
Requires-Dist: allure-pytest
Dynamic: license-file
